{
  "action": "jumpback_source_card",
  "index": 5,
  "sourceCards": [
    {
      "index": 0,
      "testId": "mindmap-source-card-node_1",
      "nodeId": "node_1",
      "sourceRefIds": [
        "src_page_7daa9d4a67aa8102_0057",
        "src_page_7daa9d4a67aa8102_0058",
        "src_page_7daa9d4a67aa8102_0068",
        "src_page_7daa9d4a67aa8102_0066",
        "src_page_7daa9d4a67aa8102_0055",
        "src_page_7daa9d4a67aa8102_0073",
        "src_page_7daa9d4a67aa8102_0047"
      ],
      "label": "核心要点",
      "excerpt": "【山海归墟】第558集：伏羲古神安然退走，原始人抵达帝盟 (https://cm.bilibili.com/cm/api/fees/pc/sync/v2?msg=a%7C5614%2Cb%7Cbilibili%2Cc%7C1%2Cd%7C0%2Ce%7CCLXH%2BhUQw5bByAEY3%2FauwAgg5wEoATCcrV047itCHzE3ODI3NTYxNDMwNjdxMTBhODVhOTdhMTQ5cTU1NDBI29%2BvpPEzUgbmrabmsYlaBua"
    },
    {
      "index": 1,
      "testId": "mindmap-source-card-node_7",
      "nodeId": "node_7",
      "sourceRefIds": [
        "src_page_7daa9d4a67aa8102_0076",
        "src_page_7daa9d4a67aa8102_0075"
      ],
      "label": "视频与内容",
      "excerpt": "直播中歌势极品甜妹音新v (https://live.bilibili.com/1933488812?hotRank=0&live_from=81003)"
    },
    {
      "index": 2,
      "testId": "mindmap-source-card-node_2",
      "nodeId": "node_2",
      "sourceRefIds": [
        "src_page_7daa9d4a67aa8102_0057"
      ],
      "label": "山海归墟 第558集：伏羲古神安然退走，原始人抵达帝盟",
      "excerpt": "【山海归墟】第558集：伏羲古神安然退走，原始人抵达帝盟 (https://cm.bilibili.com/cm/api/fees/pc/sync/v2?msg=a%7C5614%2Cb%7Cbilibili%2Cc%7C1%2Cd%7C0%2Ce%7CCLXH%2BhUQw5bByAEY3%2FauwAgg5wEoATCcrV047itCHzE3ODI3NTYxNDMwNjdxMTBhODVhOTdhMTQ5cTU1NDBI29%2BvpPEzUgbmrabmsYlaBua"
    },
    {
      "index": 3,
      "testId": "mindmap-source-card-node_3",
      "nodeId": "node_3",
      "sourceRefIds": [
        "src_page_7daa9d4a67aa8102_0058"
      ],
      "label": "奇遇原始人 06-27",
      "excerpt": "奇遇原始人· 06-27 (https://cm.bilibili.com/cm/api/fees/pc/sync/v2?msg=a%7C5614%2Cb%7Cbilibili%2Cc%7C1%2Cd%7C0%2Ce%7CCLXH%2BhUQw5bByAEY3%2FauwAgg5wEoATCcrV047itCHzE3ODI3NTYxNDMwNjdxMTBhODVhOTdhMTQ5cTU1NDBI29%2BvpPEzUgbmrabmsYlaBua5luWMl2IG5Lit5Zu"
    },
    {
      "index": 4,
      "testId": "mindmap-source-card-node_4",
      "nodeId": "node_4",
      "sourceRefIds": [
        "src_page_7daa9d4a67aa8102_0068"
      ],
      "label": "Leo朝朝- 06-28",
      "excerpt": "Leo朝朝-· 06-28 (https://cm.bilibili.com/cm/api/fees/pc/sync/v2?msg=a%7C5614%2Cb%7Cbilibili%2Cc%7C1%2Cd%7C0%2Ce%7CCIDTgBYQ9eiUyAEY4vPjvggg5gEoATD%2BxawBOO4rQh8xNzgyNzU2MTQzMDY3cTEwYTg1YTk3YTE0OXE1NTQwSNvfr6TxM1IG5q2m5rGJWgbmuZbljJdiBuS4reWbvW"
    },
    {
      "index": 5,
      "testId": "mindmap-source-card-node_8",
      "nodeId": "node_8",
      "sourceRefIds": [
        "src_page_7daa9d4a67aa8102_0076"
      ],
      "label": "直播中歌势极品甜妹音新v",
      "excerpt": "直播中歌势极品甜妹音新v (https://live.bilibili.com/1933488812?hotRank=0&live_from=81003)"
    },
    {
      "index": 6,
      "testId": "mindmap-source-card-node_9",
      "nodeId": "node_9",
      "sourceRefIds": [
        "src_page_7daa9d4a67aa8102_0066"
      ],
      "label": "10分钟吃完50串红柳大串，可获得奖金588元！能吃饱吗",
      "excerpt": "10分钟吃完50串红柳大串，可获得奖金588元！能吃饱吗 (https://www.bilibili.com/video/BV1q1EC6KECc)"
    },
    {
      "index": 7,
      "testId": "mindmap-source-card-node_10",
      "nodeId": "node_10",
      "sourceRefIds": [
        "src_page_7daa9d4a67aa8102_0075"
      ],
      "label": "直播329唱见电台",
      "excerpt": "直播329唱见电台 (https://live.bilibili.com/1933488812?hotRank=0&live_from=81003)"
    }
  ],
  "evidenceText": "直播中歌势极品甜妹音新v直播中歌势极品甜妹音新v (https://live.bilibili.com/1933488812?hotRank=0&live_from=81003)已定位并高亮来源。",
  "sourceEvidenceVisible": true,
  "status": "highlighted",
  "selectedSourceCardIndex": 5,
  "selectedSourceCardReason": "candidate score 30 for bilibili; label=直播中歌势极品甜妹音新v",
  "sourceCardAttemptCount": 1,
  "sourceCardAttempts": [
    {
      "index": 5,
      "status": "highlighted",
      "reason": "candidate score 30 for bilibili; label=直播中歌势极品甜妹音新v",
      "failureReason": null
    }
  ],
  "sourceCardCandidates": [
    {
      "index": 5,
      "label": "直播中歌势极品甜妹音新v",
      "excerpt": "直播中歌势极品甜妹音新v (https://live.bilibili.com/1933488812?hotRank=0&live_from=81003)",
      "score": 30
    },
    {
      "index": 6,
      "label": "10分钟吃完50串红柳大串，可获得奖金588元！能吃饱吗",
      "excerpt": "10分钟吃完50串红柳大串，可获得奖金588元！能吃饱吗 (https://www.bilibili.com/video/BV1q1EC6KECc)",
      "score": 30
    },
    {
      "index": 7,
      "label": "直播329唱见电台",
      "excerpt": "直播329唱见电台 (https://live.bilibili.com/1933488812?hotRank=0&live_from=81003)",
      "score": 30
    },
    {
      "index": 1,
      "label": "视频与内容",
      "excerpt": "直播中歌势极品甜妹音新v (https://live.bilibili.com/1933488812?hotRank=0&live_from=81003)",
      "score": 14
    },
    {
      "index": 2,
      "label": "山海归墟 第558集：伏羲古神安然退走，原始人抵达帝盟",
      "excerpt": "【山海归墟】第558集：伏羲古神安然退走，原始人抵达帝盟 (https://cm.bilibili.com/cm/api/fees/pc/sync/v2?msg=a%7C5614%2Cb%7Cbilibili%2Cc%7C1%2Cd%7C0%2Ce%7CCLXH%2BhUQw5bByAEY3%2FauwAgg5wEoATCcrV047itCHzE3ODI3NTYxNDMwNjdxMTBhODVhOTdhMTQ5cTU1NDBI29%2BvpPEzUgbmrabmsYlaBua",
      "score": 12
    },
    {
      "index": 3,
      "label": "奇遇原始人 06-27",
      "excerpt": "奇遇原始人· 06-27 (https://cm.bilibili.com/cm/api/fees/pc/sync/v2?msg=a%7C5614%2Cb%7Cbilibili%2Cc%7C1%2Cd%7C0%2Ce%7CCLXH%2BhUQw5bByAEY3%2FauwAgg5wEoATCcrV047itCHzE3ODI3NTYxNDMwNjdxMTBhODVhOTdhMTQ5cTU1NDBI29%2BvpPEzUgbmrabmsYlaBua5luWMl2IG5Lit5Zu",
      "score": 12
    }
  ]
}