{
  "action": "jumpback_source_card",
  "index": 0,
  "sourceCards": [
    {
      "index": 0,
      "testId": "mindmap-source-card-node_3",
      "nodeId": "node_3",
      "sourceRefIds": [
        "src_page_d9df1c246b300f3e_0058"
      ],
      "label": "背景原因",
      "excerpt": "6月17日 09:00 梅西戴帽问鼎世界杯历史射手王！ 阿根廷 小组赛 J组 3 : 0 阿尔及利亚 查看回放"
    },
    {
      "index": 1,
      "testId": "mindmap-source-card-node_4",
      "nodeId": "node_4",
      "sourceRefIds": [
        "src_page_d9df1c246b300f3e_0058"
      ],
      "label": "6月17日 09 00 梅西戴帽问鼎世界杯历史射手王！ 阿根廷",
      "excerpt": "6月17日 09:00 梅西戴帽问鼎世界杯历史射手王！ 阿根廷 小组赛 J组 3 : 0 阿尔及利亚 查看回放"
    },
    {
      "index": 2,
      "testId": "mindmap-source-card-node_5",
      "nodeId": "node_5",
      "sourceRefIds": [
        "src_page_d9df1c246b300f3e_0073"
      ],
      "label": "6月18日 10 00 迪亚斯传射建功",
      "excerpt": "6月18日 10:00 迪亚斯传射建功，哥伦比亚开门红 乌兹别克斯坦 小组赛 K组 1 : 3 哥伦比亚 查看回放"
    },
    {
      "index": 3,
      "testId": "mindmap-source-card-node_6",
      "nodeId": "node_6",
      "sourceRefIds": [
        "src_page_d9df1c246b300f3e_0034"
      ],
      "label": "6月15日 07 00 阿马德一锤定音",
      "excerpt": "6月15日 07:00 阿马德一锤定音，绝杀厄瓜多尔 科特迪瓦 小组赛 E组 1 : 0 厄瓜多尔 查看回放"
    },
    {
      "index": 4,
      "testId": "mindmap-source-card-node_7",
      "nodeId": "node_7",
      "sourceRefIds": [
        "src_page_d9df1c246b300f3e_0013"
      ],
      "label": "6月13日 09 00 巴洛贡梅开二度 美国轻取首胜 美国",
      "excerpt": "6月13日 09:00 巴洛贡梅开二度 美国轻取首胜 美国 小组赛 D组 4 : 1 巴拉圭 查看回放"
    },
    {
      "index": 5,
      "testId": "mindmap-source-card-node_8",
      "nodeId": "node_8",
      "sourceRefIds": [
        "src_page_d9df1c246b300f3e_0022"
      ],
      "label": "6月14日 09 00 麦金一锤定音",
      "excerpt": "6月14日 09:00 麦金一锤定音，风笛军团首胜 海地 小组赛 C组 0 : 1 苏格兰 查看回放"
    },
    {
      "index": 6,
      "testId": "mindmap-source-card-node_1",
      "nodeId": "node_1",
      "sourceRefIds": [
        "src_page_d9df1c246b300f3e_0102",
        "src_page_d9df1c246b300f3e_0073",
        "src_page_d9df1c246b300f3e_0034",
        "src_page_d9df1c246b300f3e_0013",
        "src_page_d9df1c246b300f3e_0022",
        "src_page_d9df1c246b300f3e_0037",
        "src_page_d9df1c246b300f3e_0055",
        "src_page_d9df1c246b300f3e_0067",
        "src_page_d9df1c246b300f3e_0085",
        "src_page_d9df1c246b300f3e_0088",
        "src_page_d9df1c246b300f3e_0097",
        "src_page_d9df1c246b300f3e_0007",
        "src_page_d9df1c246b300f3e_0028",
        "src_page_d9df1c246b300f3e_0070",
        "src_page_d9df1c246b300f3e_0079",
        "src_page_d9df1c246b300f3e_0082",
        "src_page_d9df1c246b300f3e_0091"
      ],
      "label": "核心要点",
      "excerpt": "热门 世界杯小组赛十大名场面回顾 6月12日 03:00 墨西哥主场轻取南非 墨西哥 小组赛 A组 2 : 0 南非 查看回放 6月12日 10:00 太极虎让一追二 亚洲首胜 韩国 小组赛 A组 2 : 1 捷克 查看回放 6月13日 03:00 拉林救主 加拿大拒绝开门黑 加拿大 小组赛 B组 1 : 1 波黑 查看回放 6月13日 09:00 巴洛贡梅开二度 美国轻取首胜 美国 小组赛 D组 4 : 1 巴拉圭 查看回放 6月14日 03:00 补时绝平 亚洲冠军获历史"
    },
    {
      "index": 7,
      "testId": "mindmap-source-card-node_2",
      "nodeId": "node_2",
      "sourceRefIds": [
        "src_page_d9df1c246b300f3e_0102"
      ],
      "label": "世界杯小组赛十大名场面回顾 6月12日 03 00",
      "excerpt": "热门 世界杯小组赛十大名场面回顾 6月12日 03:00 墨西哥主场轻取南非 墨西哥 小组赛 A组 2 : 0 南非 查看回放 6月12日 10:00 太极虎让一追二 亚洲首胜 韩国 小组赛 A组 2 : 1 捷克 查看回放 6月13日 03:00 拉林救主 加拿大拒绝开门黑 加拿大 小组赛 B组 1 : 1 波黑 查看回放 6月13日 09:00 巴洛贡梅开二度 美国轻取首胜 美国 小组赛 D组 4 : 1 巴拉圭 查看回放 6月14日 03:00 补时绝平 亚洲冠军获历史"
    }
  ],
  "evidenceText": "背景原因6月17日 09:00 梅西戴帽问鼎世界杯历史射手王！ 阿根廷 小组赛 J组 3 : 0 阿尔及利亚 查看回放已定位并高亮来源。",
  "sourceEvidenceVisible": true,
  "status": "highlighted",
  "selectedSourceCardIndex": 0,
  "selectedSourceCardReason": "candidate score 16 for xiaohongshu; label=背景原因",
  "sourceCardAttemptCount": 1,
  "sourceCardAttempts": [
    {
      "index": 0,
      "status": "highlighted",
      "reason": "candidate score 16 for xiaohongshu; label=背景原因",
      "failureReason": null
    }
  ],
  "sourceCardCandidates": [
    {
      "index": 0,
      "label": "背景原因",
      "excerpt": "6月17日 09:00 梅西戴帽问鼎世界杯历史射手王！ 阿根廷 小组赛 J组 3 : 0 阿尔及利亚 查看回放",
      "score": 16
    },
    {
      "index": 1,
      "label": "6月17日 09 00 梅西戴帽问鼎世界杯历史射手王！ 阿根廷",
      "excerpt": "6月17日 09:00 梅西戴帽问鼎世界杯历史射手王！ 阿根廷 小组赛 J组 3 : 0 阿尔及利亚 查看回放",
      "score": 16
    },
    {
      "index": 2,
      "label": "6月18日 10 00 迪亚斯传射建功",
      "excerpt": "6月18日 10:00 迪亚斯传射建功，哥伦比亚开门红 乌兹别克斯坦 小组赛 K组 1 : 3 哥伦比亚 查看回放",
      "score": 16
    },
    {
      "index": 3,
      "label": "6月15日 07 00 阿马德一锤定音",
      "excerpt": "6月15日 07:00 阿马德一锤定音，绝杀厄瓜多尔 科特迪瓦 小组赛 E组 1 : 0 厄瓜多尔 查看回放",
      "score": 16
    },
    {
      "index": 4,
      "label": "6月13日 09 00 巴洛贡梅开二度 美国轻取首胜 美国",
      "excerpt": "6月13日 09:00 巴洛贡梅开二度 美国轻取首胜 美国 小组赛 D组 4 : 1 巴拉圭 查看回放",
      "score": 16
    },
    {
      "index": 5,
      "label": "6月14日 09 00 麦金一锤定音",
      "excerpt": "6月14日 09:00 麦金一锤定音，风笛军团首胜 海地 小组赛 C组 0 : 1 苏格兰 查看回放",
      "score": 16
    }
  ]
}