{
  "action": "jumpback_source_card",
  "index": 0,
  "sourceCards": [
    {
      "index": 0,
      "testId": "mindmap-source-card-node_3",
      "nodeId": "node_3",
      "sourceRefIds": [
        "src_page_864f5495a73b2548_0108"
      ],
      "label": "He is more than repaying",
      "excerpt": "He is more than repaying his coach’s faith 7h ago Bosnia and HerzegovinaUS performance stirs mixed emotions in St Louis community Folarin BalogunWhy the US forward's red card will not be be struck off Big interview Cape Verde’s Sidny Lopes"
    },
    {
      "index": 1,
      "testId": "mindmap-source-card-node_1",
      "nodeId": "node_1",
      "sourceRefIds": [
        "src_page_864f5495a73b2548_0118",
        "src_page_864f5495a73b2548_0108",
        "src_page_864f5495a73b2548_0121",
        "src_page_864f5495a73b2548_0029",
        "src_page_864f5495a73b2548_0107",
        "src_page_864f5495a73b2548_0111",
        "src_page_864f5495a73b2548_0104",
        "src_page_864f5495a73b2548_0090",
        "src_page_864f5495a73b2548_0091",
        "src_page_864f5495a73b2548_0034",
        "src_page_864f5495a73b2548_0062",
        "src_page_864f5495a73b2548_0106",
        "src_page_864f5495a73b2548_0030",
        "src_page_864f5495a73b2548_0103",
        "src_page_864f5495a73b2548_0054",
        "src_page_864f5495a73b2548_0014",
        "src_page_864f5495a73b2548_0009",
        "src_page_864f5495a73b2548_0011"
      ],
      "label": "核心要点",
      "excerpt": "This film joins a group of caregivers in east London as they reclaim a few hours of their teenage lives You may have missed UFOs The Harvard astronomer dubbed Trump’s chief alien hunter starts by assuming UFOs human-made America at 250 ‘I w"
    },
    {
      "index": 2,
      "testId": "mindmap-source-card-node_2",
      "nodeId": "node_2",
      "sourceRefIds": [
        "src_page_864f5495a73b2548_0118"
      ],
      "label": "This film joins group of",
      "excerpt": "This film joins a group of caregivers in east London as they reclaim a few hours of their teenage lives You may have missed UFOs The Harvard astronomer dubbed Trump’s chief alien hunter starts by assuming UFOs human-made America at 250 ‘I w"
    },
    {
      "index": 3,
      "testId": "mindmap-source-card-node_4",
      "nodeId": "node_4",
      "sourceRefIds": [
        "src_page_864f5495a73b2548_0121"
      ],
      "label": "It s Caroline Aherne s 10",
      "excerpt": "It’s Caroline Aherne’s 10 best moments Ohio authorities rescue 16 children confined to one room for four years Trump is avoiding the World Cup because it’s packed with good things he doesn’t like Harry Kane the one who saves Tuchel as Engla"
    },
    {
      "index": 4,
      "testId": "mindmap-source-card-node_5",
      "nodeId": "node_5",
      "sourceRefIds": [
        "src_page_864f5495a73b2548_0029"
      ],
      "label": "News Ukraine At least 21",
      "excerpt": "News Ukraine At least 21 dead as Russia launches massive drone and missile attack on Kyiv More than 70 missiles fired at Ukraine capital as Russia faces fuel shortages after strikes against its oil refineries 6h ago RussiaRussia ‘mounted dr"
    },
    {
      "index": 5,
      "testId": "mindmap-source-card-node_6",
      "nodeId": "node_6",
      "sourceRefIds": [
        "src_page_864f5495a73b2548_0107"
      ],
      "label": "Trump is avoiding World",
      "excerpt": "Trump is avoiding the World Cup because it’s packed with good things he doesn’t like Barney Ronay For all its gloss and elitist governance, football will not bend to the will of a president so eager to demonise and exclude 6h ago Interactiv"
    },
    {
      "index": 6,
      "testId": "mindmap-source-card-root",
      "nodeId": "root",
      "sourceRefIds": [
        "src_page_864f5495a73b2548_0001",
        "src_page_864f5495a73b2548_0002",
        "src_page_864f5495a73b2548_0003",
        "src_page_864f5495a73b2548_0004"
      ],
      "label": "Latest news, sport and opinion from Guardian",
      "excerpt": "World Cup live Spain v Austria"
    }
  ],
  "evidenceText": "He is more than repayinglocatedHe is more than repaying his coach’s faith 7h ago Bosnia and HerzegovinaUS performance stirs mixed emotions in St Louis community Folarin BalogunWhy the US forward's red card will not be be struck off Big interview Cape Verde’s Sidny Lopes已定位并高亮来源。",
  "sourceEvidenceVisible": true,
  "status": "highlighted",
  "selectedSourceCardIndex": 0,
  "selectedSourceCardReason": "candidate score 16 for the-guardian; label=He is more than repaying",
  "sourceCardAttemptCount": 1,
  "sourceCardAttempts": [
    {
      "index": 0,
      "status": "highlighted",
      "reason": "candidate score 16 for the-guardian; label=He is more than repaying",
      "failureReason": null
    }
  ],
  "sourceCardCandidates": [
    {
      "index": 0,
      "label": "He is more than repaying",
      "excerpt": "He is more than repaying his coach’s faith 7h ago Bosnia and HerzegovinaUS performance stirs mixed emotions in St Louis community Folarin BalogunWhy the US forward's red card will not be be struck off Big interview Cape Verde’s Sidny Lopes",
      "score": 16
    },
    {
      "index": 2,
      "label": "This film joins group of",
      "excerpt": "This film joins a group of caregivers in east London as they reclaim a few hours of their teenage lives You may have missed UFOs The Harvard astronomer dubbed Trump’s chief alien hunter starts by assuming UFOs human-made America at 250 ‘I w",
      "score": 16
    },
    {
      "index": 3,
      "label": "It s Caroline Aherne s 10",
      "excerpt": "It’s Caroline Aherne’s 10 best moments Ohio authorities rescue 16 children confined to one room for four years Trump is avoiding the World Cup because it’s packed with good things he doesn’t like Harry Kane the one who saves Tuchel as Engla",
      "score": 16
    },
    {
      "index": 4,
      "label": "News Ukraine At least 21",
      "excerpt": "News Ukraine At least 21 dead as Russia launches massive drone and missile attack on Kyiv More than 70 missiles fired at Ukraine capital as Russia faces fuel shortages after strikes against its oil refineries 6h ago RussiaRussia ‘mounted dr",
      "score": 16
    },
    {
      "index": 5,
      "label": "Trump is avoiding World",
      "excerpt": "Trump is avoiding the World Cup because it’s packed with good things he doesn’t like Barney Ronay For all its gloss and elitist governance, football will not bend to the will of a president so eager to demonise and exclude 6h ago Interactiv",
      "score": 16
    },
    {
      "index": 1,
      "label": "核心要点",
      "excerpt": "This film joins a group of caregivers in east London as they reclaim a few hours of their teenage lives You may have missed UFOs The Harvard astronomer dubbed Trump’s chief alien hunter starts by assuming UFOs human-made America at 250 ‘I w",
      "score": -2
    }
  ]
}