{
  "title": "Yahoo News: Latest and Breaking News, Headlines, Live Updates, and More",
  "url": "https://www.yahoo.com/news/",
  "bodyTextLength": 3704,
  "bodyTextSample": "Search query News Finance Sports More Mail Sign in News US Politics Science World Weather News Originals Democratic socialist Melat Kiros defeats 15-term congresswoman in Colorado Melat Kiros toppled Rep. Diana DeGette in the latest primary victory for a progressive challenger over a House incumbent. Yahoo News 23K Traditionalist Catholic bishops rebel against Pope Leo XIV with 'schismatic act' Associated Press 257 High earners rush to use 'big beautiful bill' vacation rental tax break Business Insider 137 Sen. Michael Bennet loses Colorado governor primary in race shaped by Trump NBC News 1.3",
  "anchorCount": 373,
  "anchors": [
    {
      "text": "News",
      "href": "https://www.yahoo.com/"
    },
    {
      "text": "Today's news",
      "href": "https://www.yahoo.com/news/"
    },
    {
      "text": "US",
      "href": "https://www.yahoo.com/news/us/"
    },
    {
      "text": "Politics",
      "href": "https://www.yahoo.com/news/politics/"
    },
    {
      "text": "World",
      "href": "https://www.yahoo.com/news/world/"
    },
    {
      "text": "Weather",
      "href": "https://weather.yahoo.com/"
    },
    {
      "text": "Climate change",
      "href": "https://www.yahoo.com/issues/climate-change/"
    },
    {
      "text": "Science",
      "href": "https://www.yahoo.com/news/science/"
    },
    {
      "text": "Originals",
      "href": "https://www.yahoo.com/guides/originals/"
    },
    {
      "text": "Newsletters",
      "href": "https://www.yahoo.com/newsletters/"
    },
    {
      "text": "Games",
      "href": "https://www.yahoo.com/games"
    },
    {
      "text": "Life",
      "href": "https://www.yahoo.com/lifestyle/"
    },
    {
      "text": "Health",
      "href": "https://health.yahoo.com/"
    },
    {
      "text": "Parenting",
      "href": "https://www.yahoo.com/lifestyle/family-relationships/"
    },
    {
      "text": "Horoscopes",
      "href": "https://www.yahoo.com/lifestyle/horoscope/"
    },
    {
      "text": "Shopping",
      "href": "https://shopping.yahoo.com/"
    },
    {
      "text": "Food",
      "href": "https://www.yahoo.com/lifestyle/food-drink/"
    },
    {
      "text": "Travel",
      "href": "https://travel.yahoo.com/"
    },
    {
      "text": "Autos",
      "href": "https://autos.yahoo.com/"
    },
    {
      "text": "Gift ideas",
      "href": "https://shopping.yahoo.com/gift-ideas/"
    },
    {
      "text": "Buying guides",
      "href": "https://shopping.yahoo.com/guides/"
    },
    {
      "text": "Entertainment",
      "href": "https://www.yahoo.com/entertainment/"
    },
    {
      "text": "Celebrity",
      "href": "https://www.yahoo.com/entertainment/celebrity/"
    },
    {
      "text": "TV",
      "href": "https://www.yahoo.com/entertainment/tv/"
    },
    {
      "text": "Movies",
      "href": "https://www.yahoo.com/entertainment/movies/"
    },
    {
      "text": "Music",
      "href": "https://www.yahoo.com/entertainment/music/"
    },
    {
      "text": "How to Watch",
      "href": "https://www.yahoo.com/guides/how-to-watch/"
    },
    {
      "text": "Interviews",
      "href": "https://www.yahoo.com/guides/interviews/"
    },
    {
      "text": "Videos",
      "href": "https://www.yahoo.com/guides/videos/"
    },
    {
      "text": "Finance",
      "href": "https://finance.yahoo.com/"
    },
    {
      "text": "My portfolio",
      "href": "https://finance.yahoo.com/portfolios/"
    },
    {
      "text": "News",
      "href": "https://finance.yahoo.com/news/"
    },
    {
      "text": "Markets",
      "href": "https://finance.yahoo.com/markets/"
    },
    {
      "text": "Research",
      "href": "https://finance.yahoo.com/research-hub/screener/"
    },
    {
      "text": "Community",
      "href": "https://finance.yahoo.com/community/"
    },
    {
      "text": "Personal finance",
      "href": "https://finance.yahoo.com/personal-finance/"
    },
    {
      "text": "Videos",
      "href": "https://finance.yahoo.com/videos/"
    },
    {
      "text": "AlphaSpace",
      "href": "https://finance.yahoo.com/about/promos/gold/alphaspace/"
    },
    {
      "text": "Sports",
      "href": "https://sports.yahoo.com/"
    },
    {
      "text": "Fantasy",
      "href": "https://sports.yahoo.com/fantasy/"
    },
    {
      "text": "NFL",
      "href": "https://sports.yahoo.com/nfl/"
    },
    {
      "text": "NBA",
      "href": "https://sports.yahoo.com/nba/"
    },
    {
      "text": "MLB",
      "href": "https://sports.yahoo.com/mlb/"
    },
    {
      "text": "NHL",
      "href": "https://sports.yahoo.com/nhl/"
    },
    {
      "text": "College football",
      "href": "https://sports.yahoo.com/college-football/"
    },
    {
      "text": "College basketball",
      "href": "https://sports.yahoo.com/college-basketball/"
    },
    {
      "text": "Soccer",
      "href": "https://sports.yahoo.com/soccer/"
    },
    {
      "text": "Betting",
      "href": "https://sports.yahoo.com/betting/"
    },
    {
      "text": "Yahoo Sports AM",
      "href": "https://sports.yahoo.com/newsletters/yahoo-sports-am/"
    },
    {
      "text": "Show all",
      "href": "https://sports.yahoo.com/"
    },
    {
      "text": "Yahoo Scout",
      "href": "https://scout.yahoo.com/?fr=fp-more-sct&fr2=p:fp,m:more-sct"
    },
    {
      "text": "Creators",
      "href": "https://creators.yahoo.com/"
    },
    {
      "text": "Tech",
      "href": "https://tech.yahoo.com/"
    },
    {
      "text": "Local",
      "href": "https://local.yahoo.com/"
    },
    {
      "text": "USEnglish",
      "href": "https://www.yahoo.com/?p=dnr"
    },
    {
      "text": "US y LATAMEspañol",
      "href": "https://espanol.yahoo.com/?p=dnr"
    },
    {
      "text": "AustraliaEnglish",
      "href": "https://au.yahoo.com/?p=dnr"
    },
    {
      "text": "CanadaEnglish",
      "href": "https://ca.yahoo.com/?p=dnr"
    },
    {
      "text": "CanadaFrançais",
      "href": "https://qc.yahoo.com/?p=dnr"
    },
    {
      "text": "DeutschlandDeutsch",
      "href": "https://de.yahoo.com/?p=dnr"
    },
    {
      "text": "FranceFrançais",
      "href": "https://fr.yahoo.com/?p=dnr"
    },
    {
      "text": "香港繁中",
      "href": "https://hk.yahoo.com/?p=dnr"
    },
    {
      "text": "MalaysiaEnglish",
      "href": "https://malaysia.yahoo.com/?p=dnr"
    },
    {
      "text": "New ZealandEnglish",
      "href": "https://nz.yahoo.com/?p=dnr"
    },
    {
      "text": "SingaporeEnglish",
      "href": "https://sg.yahoo.com/?p=dnr"
    },
    {
      "text": "台灣繁中",
      "href": "https://tw.yahoo.com/?p=dnr"
    },
    {
      "text": "UKEnglish",
      "href": "https://uk.yahoo.com/?p=dnr"
    },
    {
      "text": "",
      "href": "https://www.yahoo.com/news/"
    },
    {
      "text": "News",
      "href": "https://www.yahoo.com/"
    },
    {
      "text": "Finance",
      "href": "https://finance.yahoo.com/"
    },
    {
      "text": "Sports",
      "href": "https://sports.yahoo.com/"
    },
    {
      "text": "News",
      "href": "https://www.yahoo.com/"
    },
    {
      "text": "Today's news",
      "href": "https://www.yahoo.com/news/"
    },
    {
      "text": "US",
      "href": "https://www.yahoo.com/news/us/"
    },
    {
      "text": "Politics",
      "href": "https://www.yahoo.com/news/politics/"
    },
    {
      "text": "World",
      "href": "https://www.yahoo.com/news/world/"
    },
    {
      "text": "Weather",
      "href": "https://weather.yahoo.com/"
    },
    {
      "text": "Climate change",
      "href": "https://www.yahoo.com/issues/climate-change/"
    },
    {
      "text": "Science",
      "href": "https://www.yahoo.com/news/science/"
    },
    {
      "text": "Originals",
      "href": "https://www.yahoo.com/guides/originals/"
    },
    {
      "text": "Newsletters",
      "href": "https://www.yahoo.com/newsletters/"
    },
    {
      "text": "Games",
      "href": "https://www.yahoo.com/games"
    },
    {
      "text": "Life",
      "href": "https://www.yahoo.com/lifestyle/"
    },
    {
      "text": "Health",
      "href": "https://health.yahoo.com/"
    },
    {
      "text": "Parenting",
      "href": "https://www.yahoo.com/lifestyle/family-relationships/"
    },
    {
      "text": "Horoscopes",
      "href": "https://www.yahoo.com/lifestyle/horoscope/"
    },
    {
      "text": "Shopping",
      "href": "https://shopping.yahoo.com/"
    },
    {
      "text": "Food",
      "href": "https://www.yahoo.com/lifestyle/food-drink/"
    },
    {
      "text": "Travel",
      "href": "https://travel.yahoo.com/"
    },
    {
      "text": "Autos",
      "href": "https://autos.yahoo.com/"
    },
    {
      "text": "Gift ideas",
      "href": "https://shopping.yahoo.com/gift-ideas/"
    },
    {
      "text": "Buying guides",
      "href": "https://shopping.yahoo.com/guides/"
    },
    {
      "text": "Entertainment",
      "href": "https://www.yahoo.com/entertainment/"
    },
    {
      "text": "Celebrity",
      "href": "https://www.yahoo.com/entertainment/celebrity/"
    },
    {
      "text": "TV",
      "href": "https://www.yahoo.com/entertainment/tv/"
    },
    {
      "text": "Movies",
      "href": "https://www.yahoo.com/entertainment/movies/"
    },
    {
      "text": "Music",
      "href": "https://www.yahoo.com/entertainment/music/"
    },
    {
      "text": "How to Watch",
      "href": "https://www.yahoo.com/guides/how-to-watch/"
    },
    {
      "text": "Interviews",
      "href": "https://www.yahoo.com/guides/interviews/"
    },
    {
      "text": "Videos",
      "href": "https://www.yahoo.com/guides/videos/"
    },
    {
      "text": "Finance",
      "href": "https://finance.yahoo.com/"
    },
    {
      "text": "My portfolio",
      "href": "https://finance.yahoo.com/portfolios/"
    },
    {
      "text": "News",
      "href": "https://finance.yahoo.com/news/"
    },
    {
      "text": "Markets",
      "href": "https://finance.yahoo.com/markets/"
    },
    {
      "text": "Research",
      "href": "https://finance.yahoo.com/research-hub/screener/"
    },
    {
      "text": "Community",
      "href": "https://finance.yahoo.com/community/"
    },
    {
      "text": "Personal finance",
      "href": "https://finance.yahoo.com/personal-finance/"
    },
    {
      "text": "Videos",
      "href": "https://finance.yahoo.com/videos/"
    },
    {
      "text": "AlphaSpace",
      "href": "https://finance.yahoo.com/about/promos/gold/alphaspace/"
    },
    {
      "text": "Sports",
      "href": "https://sports.yahoo.com/"
    },
    {
      "text": "Fantasy",
      "href": "https://sports.yahoo.com/fantasy/"
    },
    {
      "text": "NFL",
      "href": "https://sports.yahoo.com/nfl/"
    },
    {
      "text": "NBA",
      "href": "https://sports.yahoo.com/nba/"
    },
    {
      "text": "MLB",
      "href": "https://sports.yahoo.com/mlb/"
    },
    {
      "text": "NHL",
      "href": "https://sports.yahoo.com/nhl/"
    },
    {
      "text": "College football",
      "href": "https://sports.yahoo.com/college-football/"
    },
    {
      "text": "College basketball",
      "href": "https://sports.yahoo.com/college-basketball/"
    },
    {
      "text": "Soccer",
      "href": "https://sports.yahoo.com/soccer/"
    },
    {
      "text": "Betting",
      "href": "https://sports.yahoo.com/betting/"
    },
    {
      "text": "Yahoo Sports AM",
      "href": "https://sports.yahoo.com/newsletters/yahoo-sports-am/"
    }
  ],
  "loginHints": [],
  "hasNaviaSidebar": true,
  "hasNaviaLauncher": true
}