{
  "title": "观察者网",
  "url": "https://www.guancha.cn/",
  "bodyTextLength": 17768,
  "bodyTextSample": "首页 风闻 财经 国际 军事 观出行 观金融 产经 科技 城事 视频 观察员 登录/注册 APP下载 习近平会见柬埔寨人民党主席、参议院主席洪森 习近平会见孟加拉国总理塔里克 独家视频丨习近平会见洪森：共守和平、共谋发展、共创繁荣，扎实推进中柬命运共同体建设 独家视频丨习近平会见孟加拉国总理：构建新时代中孟命运共同体 习近平会见柬埔寨人民党主席、参议院主席洪森 习近平会见孟加拉国总理塔里克 独家视频丨习近平会见洪森：共守和平、共谋发展、共创繁荣，扎实推进中柬命运共同体建设 独家视频丨习近平会见孟加拉国总理：构建新时代中孟命运共同体 习近平会见柬埔寨人民党主席、参议院主席洪森 习近平会见孟加拉国总理塔里克 独家视频丨习近平会见洪森：共守和平、共谋发展、共创繁荣，扎实推进中柬命运共同体建设 独家视频丨习近平会见孟加拉国总理：构建新时代中孟命运共同体 习近平会见柬埔寨人民党主席、参议院主席洪森 习近平会见孟加拉国总理塔里克 独家视频丨习近平会见洪森：共守和平、共谋发展、共创繁荣，扎实推进中柬命运共同体建设 独家视频丨习近平会见孟加拉国总理：构建新时代中孟命运共同体 习近平会见柬埔寨人民党主席、参议院主席洪森 习近平会见孟加拉国总理塔里克 独家视频丨习近平会见洪森：共守和平、共谋发展、共创繁荣，扎实推进中柬命运共同体建设 独家视频丨习近平会见孟加拉国总理：构建新时代中孟命运共同体 习近平会",
  "anchorCount": 1700,
  "anchors": [
    {
      "text": "",
      "href": "https://www.guancha.cn/"
    },
    {
      "text": "首页",
      "href": "https://www.guancha.cn/?s=dhshouye"
    },
    {
      "text": "风闻",
      "href": "https://user.guancha.cn/?s=dhfengwen"
    },
    {
      "text": "财经",
      "href": "https://www.guancha.cn/economy?s=dhcaijing"
    },
    {
      "text": "国际",
      "href": "https://www.guancha.cn/internation?s=dhguoji"
    },
    {
      "text": "军事",
      "href": "https://www.guancha.cn/military-affairs?s=dhjunshi"
    },
    {
      "text": "观出行",
      "href": "https://www.guancha.cn/qiche?s=dhqiche"
    },
    {
      "text": "观金融",
      "href": "https://www.guancha.cn/GuanJinRong"
    },
    {
      "text": "产经",
      "href": "https://www.guancha.cn/chanjing?s=dhchanjing"
    },
    {
      "text": "科技",
      "href": "https://www.guancha.cn/gongye%C2%B7keji?s=dhgongye%C2%B7keji"
    },
    {
      "text": "城事",
      "href": "https://www.guancha.cn/ChengShi"
    },
    {
      "text": "视频",
      "href": "https://www.guancha.cn/video/gczvideo/list.html"
    },
    {
      "text": "观察员",
      "href": "javascript:void(0)"
    },
    {
      "text": "登录/注册",
      "href": "javascript:;"
    },
    {
      "text": "手机版",
      "href": "http://m.guancha.cn/"
    },
    {
      "text": "观察者新浪微博",
      "href": "http://weibo.com/newoutlook?topnav=1&wvr=4"
    },
    {
      "text": "",
      "href": "javascript:;"
    },
    {
      "text": "添加到收藏夹",
      "href": "https://www.guancha.cn/#"
    },
    {
      "text": "更改背景颜色",
      "href": "javascript:;"
    },
    {
      "text": "",
      "href": "https://www.guancha.cn/XinShiDai"
    },
    {
      "text": "习近平会见柬埔寨人民党主席、参议院主席洪森",
      "href": "https://www.guancha.cn/politics/2026_06_26_821756.shtml"
    },
    {
      "text": "习近平会见孟加拉国总理塔里克",
      "href": "https://www.guancha.cn/politics/2026_06_26_821755.shtml"
    },
    {
      "text": "独家视频丨习近平会见洪森：共守和平、共谋发展、共创繁荣，扎实推进中柬命运共同体建设",
      "href": "https://www.guancha.cn/politics/2026_06_26_821754.shtml"
    },
    {
      "text": "独家视频丨习近平会见孟加拉国总理：构建新时代中孟命运共同体",
      "href": "https://www.guancha.cn/politics/2026_06_26_821753.shtml"
    },
    {
      "text": "习近平会见柬埔寨人民党主席、参议院主席洪森",
      "href": "https://www.guancha.cn/politics/2026_06_26_821756.shtml"
    },
    {
      "text": "习近平会见孟加拉国总理塔里克",
      "href": "https://www.guancha.cn/politics/2026_06_26_821755.shtml"
    },
    {
      "text": "独家视频丨习近平会见洪森：共守和平、共谋发展、共创繁荣，扎实推进中柬命运共同体建设",
      "href": "https://www.guancha.cn/politics/2026_06_26_821754.shtml"
    },
    {
      "text": "独家视频丨习近平会见孟加拉国总理：构建新时代中孟命运共同体",
      "href": "https://www.guancha.cn/politics/2026_06_26_821753.shtml"
    },
    {
      "text": "习近平会见柬埔寨人民党主席、参议院主席洪森",
      "href": "https://www.guancha.cn/politics/2026_06_26_821756.shtml"
    },
    {
      "text": "习近平会见孟加拉国总理塔里克",
      "href": "https://www.guancha.cn/politics/2026_06_26_821755.shtml"
    },
    {
      "text": "独家视频丨习近平会见洪森：共守和平、共谋发展、共创繁荣，扎实推进中柬命运共同体建设",
      "href": "https://www.guancha.cn/politics/2026_06_26_821754.shtml"
    },
    {
      "text": "独家视频丨习近平会见孟加拉国总理：构建新时代中孟命运共同体",
      "href": "https://www.guancha.cn/politics/2026_06_26_821753.shtml"
    },
    {
      "text": "习近平会见柬埔寨人民党主席、参议院主席洪森",
      "href": "https://www.guancha.cn/politics/2026_06_26_821756.shtml"
    },
    {
      "text": "习近平会见孟加拉国总理塔里克",
      "href": "https://www.guancha.cn/politics/2026_06_26_821755.shtml"
    },
    {
      "text": "独家视频丨习近平会见洪森：共守和平、共谋发展、共创繁荣，扎实推进中柬命运共同体建设",
      "href": "https://www.guancha.cn/politics/2026_06_26_821754.shtml"
    },
    {
      "text": "独家视频丨习近平会见孟加拉国总理：构建新时代中孟命运共同体",
      "href": "https://www.guancha.cn/politics/2026_06_26_821753.shtml"
    },
    {
      "text": "习近平会见柬埔寨人民党主席、参议院主席洪森",
      "href": "https://www.guancha.cn/politics/2026_06_26_821756.shtml"
    },
    {
      "text": "习近平会见孟加拉国总理塔里克",
      "href": "https://www.guancha.cn/politics/2026_06_26_821755.shtml"
    },
    {
      "text": "独家视频丨习近平会见洪森：共守和平、共谋发展、共创繁荣，扎实推进中柬命运共同体建设",
      "href": "https://www.guancha.cn/politics/2026_06_26_821754.shtml"
    },
    {
      "text": "独家视频丨习近平会见孟加拉国总理：构建新时代中孟命运共同体",
      "href": "https://www.guancha.cn/politics/2026_06_26_821753.shtml"
    },
    {
      "text": "习近平会见柬埔寨人民党主席、参议院主席洪森",
      "href": "https://www.guancha.cn/politics/2026_06_26_821756.shtml"
    },
    {
      "text": "习近平会见孟加拉国总理塔里克",
      "href": "https://www.guancha.cn/politics/2026_06_26_821755.shtml"
    },
    {
      "text": "独家视频丨习近平会见洪森：共守和平、共谋发展、共创繁荣，扎实推进中柬命运共同体建设",
      "href": "https://www.guancha.cn/politics/2026_06_26_821754.shtml"
    },
    {
      "text": "独家视频丨习近平会见孟加拉国总理：构建新时代中孟命运共同体",
      "href": "https://www.guancha.cn/politics/2026_06_26_821753.shtml"
    },
    {
      "text": "习近平会见柬埔寨人民党主席、参议院主席洪森",
      "href": "https://www.guancha.cn/politics/2026_06_26_821756.shtml"
    },
    {
      "text": "习近平会见孟加拉国总理塔里克",
      "href": "https://www.guancha.cn/politics/2026_06_26_821755.shtml"
    },
    {
      "text": "独家视频丨习近平会见洪森：共守和平、共谋发展、共创繁荣，扎实推进中柬命运共同体建设",
      "href": "https://www.guancha.cn/politics/2026_06_26_821754.shtml"
    },
    {
      "text": "独家视频丨习近平会见孟加拉国总理：构建新时代中孟命运共同体",
      "href": "https://www.guancha.cn/politics/2026_06_26_821753.shtml"
    },
    {
      "text": "习近平会见柬埔寨人民党主席、参议院主席洪森",
      "href": "https://www.guancha.cn/politics/2026_06_26_821756.shtml"
    },
    {
      "text": "习近平会见孟加拉国总理塔里克",
      "href": "https://www.guancha.cn/politics/2026_06_26_821755.shtml"
    },
    {
      "text": "独家视频丨习近平会见洪森：共守和平、共谋发展、共创繁荣，扎实推进中柬命运共同体建设",
      "href": "https://www.guancha.cn/politics/2026_06_26_821754.shtml"
    },
    {
      "text": "独家视频丨习近平会见孟加拉国总理：构建新时代中孟命运共同体",
      "href": "https://www.guancha.cn/politics/2026_06_26_821753.shtml"
    },
    {
      "text": "习近平会见柬埔寨人民党主席、参议院主席洪森",
      "href": "https://www.guancha.cn/politics/2026_06_26_821756.shtml"
    },
    {
      "text": "习近平会见孟加拉国总理塔里克",
      "href": "https://www.guancha.cn/politics/2026_06_26_821755.shtml"
    },
    {
      "text": "独家视频丨习近平会见洪森：共守和平、共谋发展、共创繁荣，扎实推进中柬命运共同体建设",
      "href": "https://www.guancha.cn/politics/2026_06_26_821754.shtml"
    },
    {
      "text": "独家视频丨习近平会见孟加拉国总理：构建新时代中孟命运共同体",
      "href": "https://www.guancha.cn/politics/2026_06_26_821753.shtml"
    },
    {
      "text": "“卷不死”的中国碳化硅",
      "href": "https://www.guancha.cn/haoping/2026_06_26_821757.shtml"
    },
    {
      "text": "",
      "href": "https://www.guancha.cn/haoping/2026_06_26_821757.shtml"
    },
    {
      "text": "阅读 55742",
      "href": "https://www.guancha.cn/haoping/2026_06_26_821757.shtml"
    },
    {
      "text": "评论 3",
      "href": "https://www.guancha.cn/haoping/2026_06_26_821757.shtml#comment"
    },
    {
      "text": "产业万象",
      "href": "https://www.guancha.cn/ChanYeWanXiang?s=syztbq"
    },
    {
      "text": "观察者头条",
      "href": "https://www.guancha.cn/toutiao?s=syztbq"
    },
    {
      "text": "点击进入",
      "href": "https://member.guancha.cn/gczedit/index.html"
    },
    {
      "text": "",
      "href": "https://www.guancha.cn/xinzhi/index.html"
    },
    {
      "text": "更多",
      "href": "https://www.guancha.cn/mainnews-sp/"
    },
    {
      "text": "​对话赵燕菁：楼市进入淘汰赛，未来哪些房子还能涨？",
      "href": "https://www.guancha.cn/politics/2026_06_26_821703.shtml"
    },
    {
      "text": "",
      "href": "https://www.guancha.cn/politics/2026_06_26_821703.shtml"
    },
    {
      "text": "[全文]",
      "href": "https://www.guancha.cn/politics/2026_06_26_821703.shtml"
    },
    {
      "text": "阅读 80663",
      "href": "https://www.guancha.cn/politics/2026_06_26_821703.shtml"
    },
    {
      "text": "评论 81",
      "href": "https://www.guancha.cn/politics/2026_06_26_821703.shtml#comment"
    },
    {
      "text": "思路打开",
      "href": "https://www.guancha.cn/siludakai?s=syztbq"
    },
    {
      "text": "观察者头条",
      "href": "https://www.guancha.cn/toutiao?s=syztbq"
    },
    {
      "text": "台湾有事，就是日菲有事、美国没事",
      "href": "https://www.guancha.cn/yanmo/2026_06_26_821695.shtml"
    },
    {
      "text": "",
      "href": "https://www.guancha.cn/yanmo"
    },
    {
      "text": "雁默",
      "href": "https://www.guancha.cn/yanmo"
    },
    {
      "text": "",
      "href": "https://www.guancha.cn/yanmo/2026_06_26_821695.shtml"
    },
    {
      "text": "[全文]",
      "href": "https://www.guancha.cn/yanmo/2026_06_26_821695.shtml"
    },
    {
      "text": "阅读 72150",
      "href": "https://www.guancha.cn/yanmo/2026_06_26_821695.shtml"
    },
    {
      "text": "评论 54",
      "href": "https://www.guancha.cn/yanmo/2026_06_26_821695.shtml#comment"
    },
    {
      "text": "中国经济转型，需要建立一个和土地市场相当的权益市场",
      "href": "https://www.guancha.cn/zhaoyanjing/2026_06_26_821696.shtml"
    },
    {
      "text": "",
      "href": "https://www.guancha.cn/zhaoyanjing"
    },
    {
      "text": "赵燕菁",
      "href": "https://www.guancha.cn/zhaoyanjing"
    },
    {
      "text": "",
      "href": "https://www.guancha.cn/zhaoyanjing/2026_06_26_821696.shtml"
    },
    {
      "text": "[全文]",
      "href": "https://www.guancha.cn/zhaoyanjing/2026_06_26_821696.shtml"
    },
    {
      "text": "阅读 39461",
      "href": "https://www.guancha.cn/zhaoyanjing/2026_06_26_821696.shtml"
    },
    {
      "text": "评论 41",
      "href": "https://www.guancha.cn/zhaoyanjing/2026_06_26_821696.shtml#comment"
    },
    {
      "text": "当下我国禁毒战场存在一大痛点",
      "href": "https://www.guancha.cn/zuoweixin/2026_06_26_821655.shtml"
    },
    {
      "text": "",
      "href": "https://www.guancha.cn/zuoweixin"
    },
    {
      "text": "左玮",
      "href": "https://www.guancha.cn/zuoweixin"
    },
    {
      "text": "",
      "href": "https://www.guancha.cn/zuoweixin/2026_06_26_821655.shtml"
    },
    {
      "text": "[全文]",
      "href": "https://www.guancha.cn/zuoweixin/2026_06_26_821655.shtml"
    },
    {
      "text": "阅读 56999",
      "href": "https://www.guancha.cn/zuoweixin/2026_06_26_821655.shtml"
    },
    {
      "text": "评论 75",
      "href": "https://www.guancha.cn/zuoweixin/2026_06_26_821655.shtml#comment"
    },
    {
      "text": "面对美国禁令，我们要建立“数字威斯特伐利亚”",
      "href": "https://www.guancha.cn/WarwickPowell/2026_06_26_821665.shtml"
    },
    {
      "text": "",
      "href": "https://www.guancha.cn/WarwickPowell"
    },
    {
      "text": "鲍韶山",
      "href": "https://www.guancha.cn/WarwickPowell"
    },
    {
      "text": "",
      "href": "https://www.guancha.cn/WarwickPowell/2026_06_26_821665.shtml"
    },
    {
      "text": "[全文]",
      "href": "https://www.guancha.cn/WarwickPowell/2026_06_26_821665.shtml"
    },
    {
      "text": "评论 13",
      "href": "https://www.guancha.cn/WarwickPowell/2026_06_26_821665.shtml#comment"
    },
    {
      "text": "飞上天的储油罐，不仅仅是普京的烦恼",
      "href": "https://www.guancha.cn/ZhangZhongZuo/2026_06_26_821663.shtml"
    },
    {
      "text": "",
      "href": "https://www.guancha.cn/ZhangZhongZuo"
    },
    {
      "text": "张仲麟",
      "href": "https://www.guancha.cn/ZhangZhongZuo"
    },
    {
      "text": "",
      "href": "https://www.guancha.cn/ZhangZhongZuo/2026_06_26_821663.shtml"
    },
    {
      "text": "[全文]",
      "href": "https://www.guancha.cn/ZhangZhongZuo/2026_06_26_821663.shtml"
    },
    {
      "text": "阅读 87983",
      "href": "https://www.guancha.cn/ZhangZhongZuo/2026_06_26_821663.shtml"
    },
    {
      "text": "评论 95",
      "href": "https://www.guancha.cn/ZhangZhongZuo/2026_06_26_821663.shtml#comment"
    },
    {
      "text": "",
      "href": "https://www.guancha.cn/gongye%C2%B7keji"
    },
    {
      "text": "议程揭晓！「金融+端侧 AI」产业前沿论坛共启智能新局",
      "href": "https://www.guancha.cn/industry-science/2026_05_11_816581.shtml"
    },
    {
      "text": "东亚唯一的基督教大国，已悄然成为中美博弈的推手",
      "href": "https://www.guancha.cn/internation/2026_06_26_821661.shtml"
    },
    {
      "text": "",
      "href": "https://www.guancha.cn/zhouxiaolei"
    },
    {
      "text": "周晓蕾",
      "href": "https://www.guancha.cn/zhouxiaolei"
    },
    {
      "text": "",
      "href": "https://www.guancha.cn/internation/2026_06_26_821661.shtml"
    },
    {
      "text": "[全文]",
      "href": "https://www.guancha.cn/internation/2026_06_26_821661.shtml"
    },
    {
      "text": "阅读 50595",
      "href": "https://www.guancha.cn/internation/2026_06_26_821661.shtml"
    },
    {
      "text": "评论 32",
      "href": "https://www.guancha.cn/internation/2026_06_26_821661.shtml#comment"
    },
    {
      "text": "最强造船业缺工人，源于职业教育的一场“制度性错位”",
      "href": "https://www.guancha.cn/liuyuzhao/2026_06_26_821659.shtml"
    },
    {
      "text": "",
      "href": "https://www.guancha.cn/liuyuzhao"
    },
    {
      "text": "刘玉照",
      "href": "https://www.guancha.cn/liuyuzhao"
    },
    {
      "text": "",
      "href": "https://www.guancha.cn/liuyuzhao/2026_06_26_821659.shtml"
    },
    {
      "text": "[全文]",
      "href": "https://www.guancha.cn/liuyuzhao/2026_06_26_821659.shtml"
    }
  ],
  "loginHints": [
    "登录",
    "安全验证"
  ],
  "hasNaviaSidebar": true,
  "hasNaviaLauncher": true
}