{
  "action": "jumpback_source_card",
  "index": 0,
  "sourceCards": [
    {
      "index": 0,
      "testId": "mindmap-source-card-node_9",
      "nodeId": "node_9",
      "sourceRefIds": [
        "src_page_a1a3fe374ce7c9c7_0058"
      ],
      "label": "豆品 全部商品 豆瓣经典 家居生活 外出旅行 文具小物",
      "excerpt": "豆品 全部商品 豆瓣经典 家居生活 外出旅行 文具小物"
    },
    {
      "index": 1,
      "testId": "mindmap-source-card-node_10",
      "nodeId": "node_10",
      "sourceRefIds": [
        "src_page_a1a3fe374ce7c9c7_0011"
      ],
      "label": "辟谣专区 更多",
      "excerpt": "辟谣专区 · · · · · · ( 更多 )"
    },
    {
      "index": 2,
      "testId": "mindmap-source-card-node_11",
      "nodeId": "node_11",
      "sourceRefIds": [
        "src_page_a1a3fe374ce7c9c7_0015"
      ],
      "label": "精选内容 更多",
      "excerpt": "精选内容 · · · · · · ( 更多 )"
    },
    {
      "index": 3,
      "testId": "mindmap-source-card-root",
      "nodeId": "root",
      "sourceRefIds": [
        "src_page_a1a3fe374ce7c9c7_0001",
        "src_page_a1a3fe374ce7c9c7_0003",
        "src_page_a1a3fe374ce7c9c7_0004",
        "src_page_a1a3fe374ce7c9c7_0005"
      ],
      "label": "当前页面",
      "excerpt": "iOS / Android 扫码直接下载"
    },
    {
      "index": 4,
      "testId": "mindmap-source-card-node_6",
      "nodeId": "node_6",
      "sourceRefIds": [
        "src_page_a1a3fe374ce7c9c7_0073",
        "src_page_a1a3fe374ce7c9c7_0002",
        "src_page_a1a3fe374ce7c9c7_0058",
        "src_page_a1a3fe374ce7c9c7_0011",
        "src_page_a1a3fe374ce7c9c7_0015",
        "src_page_a1a3fe374ce7c9c7_0022",
        "src_page_a1a3fe374ce7c9c7_0039",
        "src_page_a1a3fe374ce7c9c7_0040",
        "src_page_a1a3fe374ce7c9c7_0042",
        "src_page_a1a3fe374ce7c9c7_0043",
        "src_page_a1a3fe374ce7c9c7_0047",
        "src_page_a1a3fe374ce7c9c7_0052",
        "src_page_a1a3fe374ce7c9c7_0060",
        "src_page_a1a3fe374ce7c9c7_0067",
        "src_page_a1a3fe374ce7c9c7_0064"
      ],
      "label": "北京 · 本周热门活动 · · · · · · ( 更多 )",
      "excerpt": "北京 · 本周热门活动 · · · · · · ( 更多 )"
    },
    {
      "index": 5,
      "testId": "mindmap-source-card-node_1",
      "nodeId": "node_1",
      "sourceRefIds": [
        "src_page_a1a3fe374ce7c9c7_0100",
        "src_page_a1a3fe374ce7c9c7_0097"
      ],
      "label": "核心要点",
      "excerpt": "一山复一水 6.80元 免费试读 脸盘大有福 达西小朋友 6.50元 免费试读 音乐 乐评 豆瓣FM 豆瓣FM 热门标签 · · · · · · ( 更多 ) [风格] OST 流行 民谣 pop indie Electronic Folk 摇滚 J-POP 电影原声 rock R&B JPOP post-rock jazz 独立音乐 电子 中国摇滚 纯音乐 古典 [地区/语言] 日本 台湾 华语 欧美 美国 内地 英国 香港 韩国 UK 粤语 大陆 US 法国 华语音乐 港"
    },
    {
      "index": 6,
      "testId": "mindmap-source-card-node_2",
      "nodeId": "node_2",
      "sourceRefIds": [
        "src_page_a1a3fe374ce7c9c7_0100"
      ],
      "label": "一山复一水 6.80元 免费试读 脸盘大有福 达西小朋",
      "excerpt": "一山复一水 6.80元 免费试读 脸盘大有福 达西小朋友 6.50元 免费试读 音乐 乐评 豆瓣FM 豆瓣FM 热门标签 · · · · · · ( 更多 ) [风格] OST 流行 民谣 pop indie Electronic Folk 摇滚 J-POP 电影原声 rock R&B JPOP post-rock jazz 独立音乐 电子 中国摇滚 纯音乐 古典 [地区/语言] 日本 台湾 华语 欧美 美国 内地 英国 香港 韩国 UK 粤语 大陆 US 法国 华语音乐 港"
    },
    {
      "index": 7,
      "testId": "mindmap-source-card-node_7",
      "nodeId": "node_7",
      "sourceRefIds": [
        "src_page_a1a3fe374ce7c9c7_0073"
      ],
      "label": "北京 本周热门活动 更多",
      "excerpt": "北京 · 本周热门活动 · · · · · · ( 更多 )"
    }
  ],
  "evidenceText": "豆品 全部商品 豆瓣经典 家居生活 外出旅行 文具小物located豆品 全部商品 豆瓣经典 家居生活 外出旅行 文具小物已定位并高亮来源。",
  "sourceEvidenceVisible": true,
  "status": "highlighted",
  "selectedSourceCardIndex": 0,
  "selectedSourceCardReason": "candidate score 16 for ; label=豆品 全部商品 豆瓣经典 家居生活 外出旅行 文具小物",
  "sourceCardAttemptCount": 1,
  "sourceCardAttempts": [
    {
      "index": 0,
      "status": "highlighted",
      "reason": "candidate score 16 for ; label=豆品 全部商品 豆瓣经典 家居生活 外出旅行 文具小物",
      "failureReason": null
    }
  ],
  "sourceCardCandidates": [
    {
      "index": 0,
      "label": "豆品 全部商品 豆瓣经典 家居生活 外出旅行 文具小物",
      "excerpt": "豆品 全部商品 豆瓣经典 家居生活 外出旅行 文具小物",
      "score": 16
    },
    {
      "index": 1,
      "label": "辟谣专区 更多",
      "excerpt": "辟谣专区 · · · · · · ( 更多 )",
      "score": 16
    },
    {
      "index": 2,
      "label": "精选内容 更多",
      "excerpt": "精选内容 · · · · · · ( 更多 )",
      "score": 16
    },
    {
      "index": 3,
      "label": "当前页面",
      "excerpt": "iOS / Android 扫码直接下载",
      "score": -2
    },
    {
      "index": 4,
      "label": "北京 · 本周热门活动 · · · · · · ( 更多 )",
      "excerpt": "北京 · 本周热门活动 · · · · · · ( 更多 )",
      "score": -14
    },
    {
      "index": 6,
      "label": "一山复一水 6.80元 免费试读 脸盘大有福 达西小朋",
      "excerpt": "一山复一水 6.80元 免费试读 脸盘大有福 达西小朋友 6.50元 免费试读 音乐 乐评 豆瓣FM 豆瓣FM 热门标签 · · · · · · ( 更多 ) [风格] OST 流行 民谣 pop indie Electronic Folk 摇滚 J-POP 电影原声 rock R&B JPOP post-rock jazz 独立音乐 电子 中国摇滚 纯音乐 古典 [地区/语言] 日本 台湾 华语 欧美 美国 内地 英国 香港 韩国 UK 粤语 大陆 US 法国 华语音乐 港",
      "score": -14
    }
  ]
}