{
  "action": "source_cards_snapshot",
  "sourceCards": [
    {
      "index": 0,
      "testId": "mindmap-source-card-node_3",
      "nodeId": "node_3",
      "sourceRefIds": [
        "src_page_77c5d269e824af04_0064",
        "src_page_77c5d269e824af04_0071",
        "src_page_77c5d269e824af04_0075",
        "src_page_77c5d269e824af04_0061",
        "src_page_77c5d269e824af04_0073",
        "src_page_77c5d269e824af04_0076",
        "src_page_77c5d269e824af04_0058",
        "src_page_77c5d269e824af04_0066",
        "src_page_77c5d269e824af04_0070",
        "src_page_77c5d269e824af04_0059",
        "src_page_77c5d269e824af04_0060",
        "src_page_77c5d269e824af04_0063",
        "src_page_77c5d269e824af04_0068"
      ],
      "label": "核心要点",
      "excerpt": "推荐世界黄金协会：下半年黄金将步入关键节点，年内或围绕4100美元交投 (https://www.thepaper.cn/newsDetail_forward_33496235)"
    },
    {
      "index": 1,
      "testId": "mindmap-source-card-node_1",
      "nodeId": "node_1",
      "sourceRefIds": [
        "src_page_77c5d269e824af04_0051",
        "src_page_77c5d269e824af04_0072"
      ],
      "label": "核心事件",
      "excerpt": "拾光纪·“时间不等人！历史不等人！”总书记要求全党同志做到“三个务必” (https://www.thepaper.cn/newsDetail_forward_33496580)"
    },
    {
      "index": 2,
      "testId": "mindmap-source-card-node_2",
      "nodeId": "node_2",
      "sourceRefIds": [
        "src_page_77c5d269e824af04_0051"
      ],
      "label": "拾光纪 时间不等人！历史不等人！ 总书记要求全党同志做到 三个务必",
      "excerpt": "拾光纪·“时间不等人！历史不等人！”总书记要求全党同志做到“三个务必” (https://www.thepaper.cn/newsDetail_forward_33496580)"
    },
    {
      "index": 3,
      "testId": "mindmap-source-card-node_4",
      "nodeId": "node_4",
      "sourceRefIds": [
        "src_page_77c5d269e824af04_0064"
      ],
      "label": "推荐世界黄金协会：下半年黄金将步入关键节点",
      "excerpt": "推荐世界黄金协会：下半年黄金将步入关键节点，年内或围绕4100美元交投 (https://www.thepaper.cn/newsDetail_forward_33496235)"
    },
    {
      "index": 4,
      "testId": "mindmap-source-card-node_5",
      "nodeId": "node_5",
      "sourceRefIds": [
        "src_page_77c5d269e824af04_0071"
      ],
      "label": "澎湃读报丨央媒头版集中刊发社论社评：热烈庆祝中国共产党成立105周年",
      "excerpt": "澎湃读报丨央媒头版集中刊发社论社评：热烈庆祝中国共产党成立105周年 (https://www.thepaper.cn/newsDetail_forward_33490978)"
    },
    {
      "index": 5,
      "testId": "mindmap-source-card-node_6",
      "nodeId": "node_6",
      "sourceRefIds": [
        "src_page_77c5d269e824af04_0075"
      ],
      "label": "法国高温求生记：去酒店 避难",
      "excerpt": "法国高温求生记：去酒店“避难”，想让幼儿园添风扇却面临“程序合规”质疑 (https://www.thepaper.cn/newsDetail_forward_33492169)"
    },
    {
      "index": 6,
      "testId": "mindmap-source-card-node_7",
      "nodeId": "node_7",
      "sourceRefIds": [
        "src_page_77c5d269e824af04_0061"
      ],
      "label": "讲武谈兵 美研发射程超1800公里空空导弹",
      "excerpt": "讲武谈兵｜美研发射程超1800公里空空导弹，异想天开还是切实可行？ (https://www.thepaper.cn/newsDetail_forward_33492239)"
    },
    {
      "index": 7,
      "testId": "mindmap-source-card-node_8",
      "nodeId": "node_8",
      "sourceRefIds": [
        "src_page_77c5d269e824af04_0072"
      ],
      "label": "中学要求新生填家长职务和车辆价格",
      "excerpt": "中学要求新生填家长职务和车辆价格，东营市教育局责令停止相关信息采集 (https://www.thepaper.cn/newsDetail_forward_33488785)"
    }
  ],
  "evidenceCardCount": 10,
  "evidenceCardLabels": [
    "核心事件",
    "拾光纪 时间不等人！历史不等人！ 总书记要求全党同志做到 三个务必",
    "核心要点",
    "推荐世界黄金协会：下半年黄金将步入关键节点",
    "澎湃读报丨央媒头版集中刊发社论社评：热烈庆祝中国共产党成立105周年",
    "法国高温求生记：去酒店 避难",
    "互动数据",
    "收藏！一图学习习近平在庆祝建党105周年大会上的讲话",
    "背景原因",
    "央视快评 牢记 三个务必 奋力创造新的历史辉煌"
  ],
  "containsEvidenceCardMindmap": true,
  "containsReadingMap": true,
  "readingMapNavCount": 11,
  "readingMapDetailText": "澎湃新闻-专注时政与思想-ThePaper.cnready庆祝中国共产党成立105周年大会在京隆重举行4 sourcedetail4 sources庆祝中国共产党成立105周年大会在京隆重举行",
  "containsSourcePanel": true,
  "sourceEvidenceVisible": false,
  "sourceEvidenceText": ""
}