{
  "action": "source_cards_snapshot",
  "sourceCards": [
    {
      "index": 0,
      "testId": "mindmap-source-card-node_9",
      "nodeId": "node_9",
      "sourceRefIds": [
        "src_page_c764dda4037fb9c1_0040",
        "src_page_c764dda4037fb9c1_0025"
      ],
      "label": "UP主与发布",
      "excerpt": "覆盖太空医疗等领域 轻舟试验飞船第二批在轨试验成果发布 今天（29日），由中国科学院微小卫星创新研究院抓总研制的轻舟试验飞船第二批在轨试验成果发布。△齿肋赤藓在轨复苏与生长观测图像，在轨验证其作为地外生态基石物种的工程应用价值"
    },
    {
      "index": 1,
      "testId": "mindmap-source-card-node_1",
      "nodeId": "node_1",
      "sourceRefIds": [
        "src_page_c764dda4037fb9c1_0089",
        "src_page_c764dda4037fb9c1_0088",
        "src_page_c764dda4037fb9c1_0087",
        "src_page_c764dda4037fb9c1_0022",
        "src_page_c764dda4037fb9c1_0007",
        "src_page_c764dda4037fb9c1_0034",
        "src_page_c764dda4037fb9c1_0023",
        "src_page_c764dda4037fb9c1_0008",
        "src_page_c764dda4037fb9c1_0035",
        "src_page_c764dda4037fb9c1_0014",
        "src_page_c764dda4037fb9c1_0021"
      ],
      "label": "核心要点",
      "excerpt": "重复使用火箭“力箭二号” 主发动机完成长程试车 近日，由中科宇航研制的110吨级液氧煤油发动机力擎二号完成连续长程鉴定试车，全面考核了该发动机的工作可靠性，未来它将成为重复使用火箭“力箭二号”的主发动机。 “算电协同”让数智生活更美好 查攻略、写文案、剪视频、搞创作……如今，AI大模型已成为很多人的案头“神器”。但你知道吗？每当让人工智能生成5秒高清视频，用电量相当于充满10部手机。最近，“豆包”新增收费模式引发关注，背后一个重要原因，正是高清视频生成、批量办... 星空有约"
    },
    {
      "index": 2,
      "testId": "mindmap-source-card-node_16",
      "nodeId": "node_16",
      "sourceRefIds": [
        "src_page_c764dda4037fb9c1_0018",
        "src_page_c764dda4037fb9c1_0036"
      ],
      "label": "其他要点",
      "excerpt": "我国科学家揭示鸟类尾巴演化的“关键拼图” 科学家们厘清了鸟类尾部演化的关键顺序，补齐了鸟类尾部演化链条中长期缺失的关键拼图。相关成果7月2日在国际学术期刊《科学进展》发表。"
    },
    {
      "index": 3,
      "testId": "mindmap-source-card-node_2",
      "nodeId": "node_2",
      "sourceRefIds": [
        "src_page_c764dda4037fb9c1_0089"
      ],
      "label": "重复使用火箭 力箭二号 主发动机完成长程试车 近日，由",
      "excerpt": "重复使用火箭“力箭二号” 主发动机完成长程试车 近日，由中科宇航研制的110吨级液氧煤油发动机力擎二号完成连续长程鉴定试车，全面考核了该发动机的工作可靠性，未来它将成为重复使用火箭“力箭二号”的主发动机。 “算电协同”让数智生活更美好 查攻略、写文案、剪视频、搞创作……如今，AI大模型已成为很多人的案头“神器”。但你知道吗？每当让人工智能生成5秒高清视频，用电量相当于充满10部手机。最近，“豆包”新增收费模式引发关注，背后一个重要原因，正是高清视频生成、批量办... 星空有约"
    },
    {
      "index": 4,
      "testId": "mindmap-source-card-node_3",
      "nodeId": "node_3",
      "sourceRefIds": [
        "src_page_c764dda4037fb9c1_0088"
      ],
      "label": "雪龙 号和 雪龙2 号破冰船亮相大连开放参观",
      "excerpt": "“雪龙”号和“雪龙2”号破冰船亮相大连开放参观 7月1日，“雪龙”号、“雪龙2”号极地科考破冰船一同亮相辽宁大连港，开启专场开放展示活动。劳动模范、高校师生、科研专家以及船舶制造企业代表等分批登船，近距离探访“双龙探极”大国重器，感悟极地精神。 我国科学家揭示鸟类尾巴演化的“关键拼图” 科学家们厘清了鸟类尾部演化的关键顺序，补齐了鸟类尾部演化链条中长期缺失的关键拼图。相关成果7月2日在国际学术期刊《科学进展》发表。 一生惠农兴农 这位农技专家获得“七一勋章” 在江苏镇江句容市"
    },
    {
      "index": 5,
      "testId": "mindmap-source-card-node_4",
      "nodeId": "node_4",
      "sourceRefIds": [
        "src_page_c764dda4037fb9c1_0087"
      ],
      "label": "列表浏览 卡片浏览 未来产业 布局新赛道 量子大道：产",
      "excerpt": "列表浏览 卡片浏览 未来产业 布局新赛道 量子大道：产业协同 “链”起未来 跟随记者的镜头，一起到安徽合肥的量子大道，去看看量子科技这个前沿的未来产业，是如何在这片土地上落地生根的。 中国第16次北冰洋考察启航 2026年7月3日，由自然资源部组织的中国第16次北冰洋考察队“雪龙”号、“雪龙2”号、北海局“极地”号从大连启航，这是“十五五”开局之年我国组织实施的首次北冰洋考察，由“雪龙”号、“雪龙2”号、北海局“极地”号、“探索三号”四... 把“上海大剧院”吊起来，拼接偏差"
    },
    {
      "index": 6,
      "testId": "mindmap-source-card-node_5",
      "nodeId": "node_5",
      "sourceRefIds": [
        "src_page_c764dda4037fb9c1_0022"
      ],
      "label": "记者探访海上 超级大冰箱 液化天然气船 今天 30日",
      "excerpt": "记者探访海上“超级大冰箱”液化天然气船 今天（30日），两艘“中国造”17.4万立方米“巨无霸”液化天然气运输船同日交付用户。如今，随着国产殷瓦钢量产和国内液化天然气运输船焊工批量培养，我国已经打通液化天然气运输船设计、材料、建造全产业链，实现了17.4万立方米LNG..."
    },
    {
      "index": 7,
      "testId": "mindmap-source-card-node_6",
      "nodeId": "node_6",
      "sourceRefIds": [
        "src_page_c764dda4037fb9c1_0007"
      ],
      "label": "把 上海大剧院 吊起来",
      "excerpt": "把“上海大剧院”吊起来，拼接偏差不超一枚硬币厚度 在上海市崇明区长兴岛的江南造船厂内，曾有过这样一个壮观的场景：两个相当于十层楼高的超大型船舶部件，总重近万吨，对接面有近千个指甲盖大小的微细对接特征，要在船坞内高效、精准地拼接在一起，误差不能超过硬币的厚度。"
    }
  ],
  "evidenceCardCount": 9,
  "evidenceCardLabels": [
    "核心要点",
    "重复使用火箭 力箭二号 主发动机完成长程试车 近日，由",
    "雪龙 号和 雪龙2 号破冰船亮相大连开放参观",
    "人物与机构",
    "短视频越刷越停不下来？专家：根源在大脑奖赏机制 不少人",
    "UP主与发布",
    "覆盖太空医疗等领域 轻舟试验飞船第二批在轨试验成果发布",
    "核心事件",
    "不少人都有这样的经历，随手点开短视频，短短几分钟的停留"
  ],
  "containsEvidenceCardMindmap": true,
  "containsReadingMap": true,
  "readingMapNavCount": 10,
  "readingMapDetailText": "科技新闻_央视网 cctv.comready温馨提示：若您的手机号已在央视网注册，绑定后， 仅保留手机账号内的信息。4 sourcedetail4 sources温馨提示：若您的手机号已在央视网注册，绑定后， 仅保留手机账号内的信息。",
  "containsSourcePanel": true,
  "sourceEvidenceVisible": false,
  "sourceEvidenceText": ""
}