{
  "title": "观察者网",
  "url": "https://www.guancha.cn/",
  "bodyTextLength": 17239,
  "bodyTextSample": "首页 风闻 财经 国际 军事 观出行 观金融 产经 科技 城事 视频 观察员 登录/注册 APP下载 习近平在庆祝中国共产党成立105周年大会上发表重要讲话 习近平为“七一勋章”获得者颁授勋章 习近平等为受表彰的全国“两优一先”代表颁奖 习近平在庆祝中国共产党成立105周年大会上发表重要讲话 习近平为“七一勋章”获得者颁授勋章 习近平等为受表彰的全国“两优一先”代表颁奖 习近平在庆祝中国共产党成立105周年大会上发表重要讲话 习近平为“七一勋章”获得者颁授勋章 习近平等为受表彰的全国“两优一先”代表颁奖 习近平在庆祝中国共产党成立105周年大会上发表重要讲话 习近平为“七一勋章”获得者颁授勋章 习近平等为受表彰的全国“两优一先”代表颁奖 习近平在庆祝中国共产党成立105周年大会上发表重要讲话 习近平为“七一勋章”获得者颁授勋章 习近平等为受表彰的全国“两优一先”代表颁奖 习近平在庆祝中国共产党成立105周年大会上发表重要讲话 习近平为“七一勋章”获得者颁授勋章 习近平等为受表彰的全国“两优一先”代表颁奖 习近平在庆祝中国共产党成立105周年大会上发表重要讲话 习近平为“七一勋章”获得者颁授勋章 习近平等为受表彰的全国“两优一先”代表颁奖 习近平在庆祝中国共产党成立105周年大会上发表重要讲话 习近平为“七一勋章”获得者颁授勋章 习近平等为受表彰的全国“两优一先”代表颁奖 习近平在庆",
  "anchorCount": 1683,
  "anchors": [
    {
      "text": "",
      "href": "https://www.guancha.cn/"
    },
    {
      "text": "首页",
      "href": "https://www.guancha.cn/?s=dhshouye"
    },
    {
      "text": "风闻",
      "href": "https://user.guancha.cn/?s=dhfengwen"
    },
    {
      "text": "财经",
      "href": "https://www.guancha.cn/economy?s=dhcaijing"
    },
    {
      "text": "国际",
      "href": "https://www.guancha.cn/internation?s=dhguoji"
    },
    {
      "text": "军事",
      "href": "https://www.guancha.cn/military-affairs?s=dhjunshi"
    },
    {
      "text": "观出行",
      "href": "https://www.guancha.cn/qiche?s=dhqiche"
    },
    {
      "text": "观金融",
      "href": "https://www.guancha.cn/GuanJinRong"
    },
    {
      "text": "产经",
      "href": "https://www.guancha.cn/chanjing?s=dhchanjing"
    },
    {
      "text": "科技",
      "href": "https://www.guancha.cn/gongye%C2%B7keji?s=dhgongye%C2%B7keji"
    },
    {
      "text": "城事",
      "href": "https://www.guancha.cn/ChengShi"
    },
    {
      "text": "视频",
      "href": "https://www.guancha.cn/video/gczvideo/list.html"
    },
    {
      "text": "观察员",
      "href": "javascript:void(0)"
    },
    {
      "text": "登录/注册",
      "href": "javascript:;"
    },
    {
      "text": "手机版",
      "href": "http://m.guancha.cn/"
    },
    {
      "text": "观察者新浪微博",
      "href": "http://weibo.com/newoutlook?topnav=1&wvr=4"
    },
    {
      "text": "",
      "href": "javascript:;"
    },
    {
      "text": "添加到收藏夹",
      "href": "https://www.guancha.cn/#"
    },
    {
      "text": "更改背景颜色",
      "href": "javascript:;"
    },
    {
      "text": "",
      "href": "https://www.guancha.cn/XinShiDai"
    },
    {
      "text": "习近平在庆祝中国共产党成立105周年大会上发表重要讲话",
      "href": "https://www.guancha.cn/politics/2026_07_01_822184.shtml"
    },
    {
      "text": "习近平为“七一勋章”获得者颁授勋章",
      "href": "https://www.guancha.cn/politics/2026_07_01_822183.shtml"
    },
    {
      "text": "习近平等为受表彰的全国“两优一先”代表颁奖",
      "href": "https://www.guancha.cn/politics/2026_07_01_822182.shtml"
    },
    {
      "text": "习近平在庆祝中国共产党成立105周年大会上发表重要讲话",
      "href": "https://www.guancha.cn/politics/2026_07_01_822184.shtml"
    },
    {
      "text": "习近平为“七一勋章”获得者颁授勋章",
      "href": "https://www.guancha.cn/politics/2026_07_01_822183.shtml"
    },
    {
      "text": "习近平等为受表彰的全国“两优一先”代表颁奖",
      "href": "https://www.guancha.cn/politics/2026_07_01_822182.shtml"
    },
    {
      "text": "习近平在庆祝中国共产党成立105周年大会上发表重要讲话",
      "href": "https://www.guancha.cn/politics/2026_07_01_822184.shtml"
    },
    {
      "text": "习近平为“七一勋章”获得者颁授勋章",
      "href": "https://www.guancha.cn/politics/2026_07_01_822183.shtml"
    },
    {
      "text": "习近平等为受表彰的全国“两优一先”代表颁奖",
      "href": "https://www.guancha.cn/politics/2026_07_01_822182.shtml"
    },
    {
      "text": "习近平在庆祝中国共产党成立105周年大会上发表重要讲话",
      "href": "https://www.guancha.cn/politics/2026_07_01_822184.shtml"
    },
    {
      "text": "习近平为“七一勋章”获得者颁授勋章",
      "href": "https://www.guancha.cn/politics/2026_07_01_822183.shtml"
    },
    {
      "text": "习近平等为受表彰的全国“两优一先”代表颁奖",
      "href": "https://www.guancha.cn/politics/2026_07_01_822182.shtml"
    },
    {
      "text": "习近平在庆祝中国共产党成立105周年大会上发表重要讲话",
      "href": "https://www.guancha.cn/politics/2026_07_01_822184.shtml"
    },
    {
      "text": "习近平为“七一勋章”获得者颁授勋章",
      "href": "https://www.guancha.cn/politics/2026_07_01_822183.shtml"
    },
    {
      "text": "习近平等为受表彰的全国“两优一先”代表颁奖",
      "href": "https://www.guancha.cn/politics/2026_07_01_822182.shtml"
    },
    {
      "text": "习近平在庆祝中国共产党成立105周年大会上发表重要讲话",
      "href": "https://www.guancha.cn/politics/2026_07_01_822184.shtml"
    },
    {
      "text": "习近平为“七一勋章”获得者颁授勋章",
      "href": "https://www.guancha.cn/politics/2026_07_01_822183.shtml"
    },
    {
      "text": "习近平等为受表彰的全国“两优一先”代表颁奖",
      "href": "https://www.guancha.cn/politics/2026_07_01_822182.shtml"
    },
    {
      "text": "习近平在庆祝中国共产党成立105周年大会上发表重要讲话",
      "href": "https://www.guancha.cn/politics/2026_07_01_822184.shtml"
    },
    {
      "text": "习近平为“七一勋章”获得者颁授勋章",
      "href": "https://www.guancha.cn/politics/2026_07_01_822183.shtml"
    },
    {
      "text": "习近平等为受表彰的全国“两优一先”代表颁奖",
      "href": "https://www.guancha.cn/politics/2026_07_01_822182.shtml"
    },
    {
      "text": "习近平在庆祝中国共产党成立105周年大会上发表重要讲话",
      "href": "https://www.guancha.cn/politics/2026_07_01_822184.shtml"
    },
    {
      "text": "习近平为“七一勋章”获得者颁授勋章",
      "href": "https://www.guancha.cn/politics/2026_07_01_822183.shtml"
    },
    {
      "text": "习近平等为受表彰的全国“两优一先”代表颁奖",
      "href": "https://www.guancha.cn/politics/2026_07_01_822182.shtml"
    },
    {
      "text": "习近平在庆祝中国共产党成立105周年大会上发表重要讲话",
      "href": "https://www.guancha.cn/politics/2026_07_01_822184.shtml"
    },
    {
      "text": "习近平为“七一勋章”获得者颁授勋章",
      "href": "https://www.guancha.cn/politics/2026_07_01_822183.shtml"
    },
    {
      "text": "习近平等为受表彰的全国“两优一先”代表颁奖",
      "href": "https://www.guancha.cn/politics/2026_07_01_822182.shtml"
    },
    {
      "text": "“人归心不归”已成往事，香港首个五年规划开始答题",
      "href": "https://www.guancha.cn/dengfei/2026_07_01_822185.shtml"
    },
    {
      "text": "",
      "href": "https://www.guancha.cn/dengfei/2026_07_01_822185.shtml"
    },
    {
      "text": "阅读 40143",
      "href": "https://www.guancha.cn/dengfei/2026_07_01_822185.shtml"
    },
    {
      "text": "评论 23",
      "href": "https://www.guancha.cn/dengfei/2026_07_01_822185.shtml#comment"
    },
    {
      "text": "点击进入",
      "href": "https://member.guancha.cn/gczedit/index.html"
    },
    {
      "text": "",
      "href": "https://www.guancha.cn/xinzhi/index.html"
    },
    {
      "text": "更多",
      "href": "https://www.guancha.cn/mainnews-sp/"
    },
    {
      "text": "开箱特朗普金色手机，499美元就这水平？",
      "href": "https://www.guancha.cn/ShenYi/2026_07_01_822157.shtml"
    },
    {
      "text": "",
      "href": "https://www.guancha.cn/ShenYi"
    },
    {
      "text": "沈逸",
      "href": "https://www.guancha.cn/ShenYi"
    },
    {
      "text": "",
      "href": "https://www.guancha.cn/ShenYi/2026_07_01_822157.shtml"
    },
    {
      "text": "[全文]",
      "href": "https://www.guancha.cn/ShenYi/2026_07_01_822157.shtml"
    },
    {
      "text": "阅读 40640",
      "href": "https://www.guancha.cn/ShenYi/2026_07_01_822157.shtml"
    },
    {
      "text": "评论 34",
      "href": "https://www.guancha.cn/ShenYi/2026_07_01_822157.shtml#comment"
    },
    {
      "text": "从李嘉诚到黎家盈，谁抓住了香港的机遇？",
      "href": "https://www.guancha.cn/MeiXinYu/2026_07_01_822164.shtml"
    },
    {
      "text": "",
      "href": "https://www.guancha.cn/MeiXinYu"
    },
    {
      "text": "梅新育",
      "href": "https://www.guancha.cn/MeiXinYu"
    },
    {
      "text": "",
      "href": "https://www.guancha.cn/MeiXinYu/2026_07_01_822164.shtml"
    },
    {
      "text": "[全文]",
      "href": "https://www.guancha.cn/MeiXinYu/2026_07_01_822164.shtml"
    },
    {
      "text": "阅读 27584",
      "href": "https://www.guancha.cn/MeiXinYu/2026_07_01_822164.shtml"
    },
    {
      "text": "评论 15",
      "href": "https://www.guancha.cn/MeiXinYu/2026_07_01_822164.shtml#comment"
    },
    {
      "text": "学美国向中国小包裹收税，欧盟是嫌民众生活成本还不够高？",
      "href": "https://www.guancha.cn/tangxiaofu/2026_07_01_822160.shtml"
    },
    {
      "text": "",
      "href": "https://www.guancha.cn/tangxiaofu"
    },
    {
      "text": "唐晓甫",
      "href": "https://www.guancha.cn/tangxiaofu"
    },
    {
      "text": "",
      "href": "https://www.guancha.cn/tangxiaofu/2026_07_01_822160.shtml"
    },
    {
      "text": "[全文]",
      "href": "https://www.guancha.cn/tangxiaofu/2026_07_01_822160.shtml"
    },
    {
      "text": "评论 12",
      "href": "https://www.guancha.cn/tangxiaofu/2026_07_01_822160.shtml#comment"
    },
    {
      "text": "秘鲁选出首位日裔女总统，中秘经贸或面临哪些考验？",
      "href": "https://www.guancha.cn/mengkexin/2026_06_30_822088.shtml"
    },
    {
      "text": "",
      "href": "https://www.guancha.cn/mengkexin"
    },
    {
      "text": "孟可心",
      "href": "https://www.guancha.cn/mengkexin"
    },
    {
      "text": "",
      "href": "https://www.guancha.cn/mengkexin/2026_06_30_822088.shtml"
    },
    {
      "text": "[全文]",
      "href": "https://www.guancha.cn/mengkexin/2026_06_30_822088.shtml"
    },
    {
      "text": "阅读 74081",
      "href": "https://www.guancha.cn/mengkexin/2026_06_30_822088.shtml"
    },
    {
      "text": "评论 70",
      "href": "https://www.guancha.cn/mengkexin/2026_06_30_822088.shtml#comment"
    },
    {
      "text": "台当局妄想抄乌克兰作业？那就惨了",
      "href": "https://www.guancha.cn/lvlishi/2026_06_30_822020.shtml"
    },
    {
      "text": "",
      "href": "https://www.guancha.cn/lvlishi"
    },
    {
      "text": "吕礼诗",
      "href": "https://www.guancha.cn/lvlishi"
    },
    {
      "text": "",
      "href": "https://www.guancha.cn/ShiYang"
    },
    {
      "text": "施洋",
      "href": "https://www.guancha.cn/ShiYang"
    },
    {
      "text": "",
      "href": "https://www.guancha.cn/lvlishi/2026_06_30_822020.shtml"
    },
    {
      "text": "[全文]",
      "href": "https://www.guancha.cn/lvlishi/2026_06_30_822020.shtml"
    },
    {
      "text": "阅读 112400",
      "href": "https://www.guancha.cn/lvlishi/2026_06_30_822020.shtml"
    },
    {
      "text": "评论 60",
      "href": "https://www.guancha.cn/lvlishi/2026_06_30_822020.shtml#comment"
    },
    {
      "text": "差到气坏总统，韩国足球大地震要来了",
      "href": "https://www.guancha.cn/yangjian1/2026_06_30_822024.shtml"
    },
    {
      "text": "",
      "href": "https://www.guancha.cn/yangjian1"
    },
    {
      "text": "杨健",
      "href": "https://www.guancha.cn/yangjian1"
    },
    {
      "text": "",
      "href": "https://www.guancha.cn/yangjian1/2026_06_30_822024.shtml"
    },
    {
      "text": "[全文]",
      "href": "https://www.guancha.cn/yangjian1/2026_06_30_822024.shtml"
    },
    {
      "text": "阅读 55018",
      "href": "https://www.guancha.cn/yangjian1/2026_06_30_822024.shtml"
    },
    {
      "text": "评论 69",
      "href": "https://www.guancha.cn/yangjian1/2026_06_30_822024.shtml#comment"
    },
    {
      "text": "",
      "href": "https://www.guancha.cn/gongye%C2%B7keji"
    },
    {
      "text": "议程揭晓！「金融+端侧 AI」产业前沿论坛共启智能新局",
      "href": "https://www.guancha.cn/industry-science/2026_05_11_816581.shtml"
    },
    {
      "text": "乌克兰前线胶着，毒品供应链却“越打越顺”",
      "href": "https://www.guancha.cn/AntonNeeleman/2026_06_30_822044.shtml"
    },
    {
      "text": "",
      "href": "https://www.guancha.cn/AntonNeeleman"
    },
    {
      "text": "安东·尼尔曼",
      "href": "https://www.guancha.cn/AntonNeeleman"
    },
    {
      "text": "",
      "href": "https://www.guancha.cn/AntonNeeleman/2026_06_30_822044.shtml"
    },
    {
      "text": "[全文]",
      "href": "https://www.guancha.cn/AntonNeeleman/2026_06_30_822044.shtml"
    },
    {
      "text": "阅读 30289",
      "href": "https://www.guancha.cn/AntonNeeleman/2026_06_30_822044.shtml"
    },
    {
      "text": "评论 19",
      "href": "https://www.guancha.cn/AntonNeeleman/2026_06_30_822044.shtml#comment"
    },
    {
      "text": "在这里西方符号无处不在，而渗透进普通人生活的是中国制造",
      "href": "https://www.guancha.cn/liyun2/2026_06_30_822027.shtml"
    },
    {
      "text": "",
      "href": "https://www.guancha.cn/liyun2"
    },
    {
      "text": "李昀",
      "href": "https://www.guancha.cn/liyun2"
    },
    {
      "text": "",
      "href": "https://www.guancha.cn/liyun2/2026_06_30_822027.shtml"
    },
    {
      "text": "[全文]",
      "href": "https://www.guancha.cn/liyun2/2026_06_30_822027.shtml"
    },
    {
      "text": "阅读 45483",
      "href": "https://www.guancha.cn/liyun2/2026_06_30_822027.shtml"
    },
    {
      "text": "评论 23",
      "href": "https://www.guancha.cn/liyun2/2026_06_30_822027.shtml#comment"
    },
    {
      "text": "汽车“变胖”是消费升级，但需要政策公平",
      "href": "https://www.guancha.cn/Sukui/2026_06_29_821956.shtml"
    },
    {
      "text": "",
      "href": "https://www.guancha.cn/Sukui"
    },
    {
      "text": "苏奎",
      "href": "https://www.guancha.cn/Sukui"
    },
    {
      "text": "",
      "href": "https://www.guancha.cn/Sukui/2026_06_29_821956.shtml"
    },
    {
      "text": "[全文]",
      "href": "https://www.guancha.cn/Sukui/2026_06_29_821956.shtml"
    },
    {
      "text": "阅读 39426",
      "href": "https://www.guancha.cn/Sukui/2026_06_29_821956.shtml"
    },
    {
      "text": "评论 51",
      "href": "https://www.guancha.cn/Sukui/2026_06_29_821956.shtml#comment"
    }
  ],
  "loginHints": [
    "登录",
    "安全验证"
  ],
  "hasNaviaSidebar": true,
  "hasNaviaLauncher": true
}